{
  "message_from" : "hyaene_general_Message.wav",
  "taunt_1"      : "hyaene_taunt_01.wav",
  "taunt_2"      : "hyaene_taunt_02.wav",
  "taunt_3"      : "hyaene_taunt_03.wav",
  "taunt_4"      : "hyaene_taunt_04.wav",
  "anger_1"      : "hyaene_anger_01.wav",
  "anger_2"      : "hyaene_anger_02.wav",
  "plead"        : "hyaene_plead_01.wav",
  "nervous_1"    : "hyaene_nervous_01.wav",
  "nervous_2"    : "hyaene_nervous_02.wav",
  "victory_1"    : "hyaene_vict_01.wav",
  "victory_2"    : "hyaene_vict_02.wav",
  "victory_3"    : "hyaene_vict_03.wav",
  "victory_4"    : "hyaene_vict_04.wav",
  "request"      : "hyaene_req_01.wav",
  "thanks"       : "hyaene_thanks_01.wav",
  "ally_death"   : "hyaene_ally_death_01.wav",
  "congrats"     : "hyaene_congrats_01.wav",
  "boast"        : "hyaene_boast_01.wav",
  "help"         : "hyaene_help_01.wav",
  "extra"        : "hyaene_extra_01.wav",
  "kick_player"  : "hyaene_kick_player_01.wav",
  "add_player"   : "hyaene_add_player_01.wav",
  "siege"        : "hyaene_siege_01.wav",
  "no_attack_1"  : "hyaene_noattack_01.wav",
  "no_attack_2"  : "hyaene_noattack_02.wav",
  "no_help_1"    : "hyaene_nohelp_01.wav",
  "no_help_2"    : "hyaene_nohelp_02.wav",
  "no_sent"      : "hyaene_notsent_01.wav",
  "sent"         : "hyaene_sent_01.wav",
  "team_losing"  : "hyaene_team_losing_01.wav",
  "team_winning" : "hyaene_team_winning_01.wav",
  "help_sent"    : "hyaene_help_01.wav",
  "will_attack"  : "hyaene_willattack_01.wav"
}